shinny_pip_index/__init__.py
shinny_pip_index/__main__.py
shinny_pip_index/cli.py
shinny_pip_index/server.py
shinny_pip_index-0.0.3.dist-info/METADATA
shinny_pip_index-0.0.3.dist-info/WHEEL
shinny_pip_index-0.0.3.dist-info/entry_points.txt
shinny_pip_index-0.0.3.dist-info/top_level.txt
shinny_pip_index-0.0.3.dist-info/RECORD
